[{"geometry":{"type":"Polygon","coordinates":[[[-73.99857331,40.78893816],[-73.99825953,40.7893425],[-73.99805193,40.78925007],[-73.9983658,40.7888458],[-73.99857331,40.78893816]]]},"type":"Feature","properties":{"kind":"building","area":1848,"sort_rank":475,"landuse_kind":"residential","scale_rank":4,"source":"openstreetmap.org","min_zoom":13,"id":404570687}},{"geometry":{"type":"Polygon","coordinates":[[[-73.99888125,40.78852498],[-73.99861732,40.78886852],[-73.99841053,40.78877738],[-73.99867437,40.78843391],[-73.99888125,40.78852498]]]},"type":"Feature","properties":{"kind":"building","area":1556,"sort_rank":475,"landuse_kind":"residential","scale_rank":4,"source":"openstreetmap.org","min_zoom":14,"id":404570686}}]